docs/conf.py
restapi/__commands__.py
restapi/__init__.py
restapi/__main__.py
restapi/alembic_env.py
restapi/config.py
restapi/customizer.py
restapi/decorators.py
restapi/env.py
restapi/exceptions.py
restapi/mocks.py
restapi/py.typed
restapi/server.py
restapi/tests.py
restapi/tests_initialization.py
restapi/types.py
restapi/connectors/__init__.py
restapi/connectors/celery/__init__.py
restapi/connectors/celery/beat.py
restapi/connectors/celery/worker.py
restapi/connectors/ftp/__init__.py
restapi/connectors/neo4j/__init__.py
restapi/connectors/neo4j/models.py
restapi/connectors/neo4j/parser.py
restapi/connectors/neo4j/types.py
restapi/connectors/rabbitmq/__init__.py
restapi/connectors/redis/__init__.py
restapi/connectors/smtp/__init__.py
restapi/connectors/smtp/mailmock.py
restapi/connectors/smtp/notifications.py
restapi/connectors/smtp/templates/__init__.py
restapi/connectors/smtp/templates/activate_account.html
restapi/connectors/smtp/templates/blocked_credentials.html
restapi/connectors/smtp/templates/celery_error_notification.html
restapi/connectors/smtp/templates/email_footer.html
restapi/connectors/smtp/templates/email_header.html
restapi/connectors/smtp/templates/new_credentials.html
restapi/connectors/smtp/templates/new_user_registered.html
restapi/connectors/smtp/templates/reset_password.html
restapi/connectors/smtp/templates/update_credentials.html
restapi/connectors/sqlalchemy/__init__.py
restapi/connectors/sqlalchemy/models.py
restapi/endpoints/__init__.py
restapi/endpoints/admin_groups.py
restapi/endpoints/admin_logins.py
restapi/endpoints/admin_server_stats.py
restapi/endpoints/admin_tokens.py
restapi/endpoints/admin_users.py
restapi/endpoints/group_users.py
restapi/endpoints/login.py
restapi/endpoints/login_unlock.py
restapi/endpoints/logout.py
restapi/endpoints/profile.py
restapi/endpoints/profile_activation.py
restapi/endpoints/profile_registration.py
restapi/endpoints/reset_password.py
restapi/endpoints/schemas.py
restapi/endpoints/send_mail.py
rapydo_http-3.0.dist-info/LICENSE
rapydo_http-3.0.dist-info/METADATA
rapydo_http-3.0.dist-info/WHEEL
rapydo_http-3.0.dist-info/entry_points.txt
rapydo_http-3.0.dist-info/top_level.txt
rapydo_http-3.0.dist-info/RECORD
